[{
  "SourceFile": "/home/vagif/Desktop/TLC00000.AVI",
  "ExifToolVersion": 10.80,
  "FileName": "TLC00000.AVI",
  "Directory": "/home/vagif/Desktop",
  "FileSize": "844 MB",
  "FileModifyDate": "2021:07:22 16:00:00+01:00",
  "FileAccessDate": "2021:08:17 11:59:40+01:00",
  "FileInodeChangeDate": "2021:08:12 15:41:18+01:00",
  "FilePermissions": "rw-r--r--",
  "FileType": "AVI",
  "FileTypeExtension": "avi",
  "MIMEType": "video/x-msvideo",
  "FrameRate": 15,
  "MaxDataRate": "19.53 kB/s",
  "FrameCount": 8951,
  "StreamCount": 1,
  "StreamType": "Video",
  "VideoCodec": "MJPG",
  "VideoFrameRate": 15,
  "VideoFrameCount": 8951,
  "Quality": "Default",
  "SampleSize": "Variable",
  "BMPVersion": "Windows V3",
  "ImageWidth": 1280,
  "ImageHeight": 720,
  "Planes": 1,
  "BitDepth": 24,
  "Compression": "MJPG",
  "ImageLength": 2764800,
  "PixelsPerMeterX": 0,
  "PixelsPerMeterY": 0,
  "NumColors": "Use BitDepth",
  "NumImportantColors": "All",
  "Duration": "0:09:56",
  "ImageSize": "1280x720",
  "Megapixels": 0.922
}]
